rpcutils/__init__.py
rpcutils/brokerRPC.py
rpcutils-3.0.dist-info/DESCRIPTION.rst
rpcutils-3.0.dist-info/LICENSE.txt
rpcutils-3.0.dist-info/METADATA
rpcutils-3.0.dist-info/RECORD
rpcutils-3.0.dist-info/WHEEL
rpcutils-3.0.dist-info/metadata.json
rpcutils-3.0.dist-info/top_level.txt
