Metadata-Version: 2.0
Name: rpcutils
Version: 3.0
Summary: RPC Utilities
Home-page: http://github.com/Caregraf/rpcutils
Author: UNKNOWN
Author-email: UNKNOWN
License: Apache License, Version 2.0
Keywords: VistA,RPC
Platform: UNKNOWN
Classifier: Development Status :: 4 - Beta
Classifier: Programming Language :: Python :: 3
Requires-Python: >=3.3, <4
